pmc_mapper.py
pmc_mapper-1.0.3.dist-info/METADATA
pmc_mapper-1.0.3.dist-info/WHEEL
pmc_mapper-1.0.3.dist-info/entry_points.txt
pmc_mapper-1.0.3.dist-info/top_level.txt
pmc_mapper-1.0.3.dist-info/RECORD
