Metadata-Version: 2.1
Name: pmc-mapper
Version: 1.0.3
Summary: A Python Library that map PubMed Central XML to Python object
Home-page: https://github.com/soultoolman/pmc-mapper
Author: soultoolman
Author-email: soultoolman@gmail.com
License: MIT
Platform: UNKNOWN
Classifier: License :: OSI Approved :: MIT License
Classifier: Programming Language :: Python
Classifier: Programming Language :: Python :: 3
Classifier: Programming Language :: Python :: 3.6
Classifier: Programming Language :: Python :: Implementation :: CPython
Classifier: Programming Language :: Python :: Implementation :: PyPy
Requires-Python: >=3.6.0
Requires-Dist: lxml
Requires-Dist: click
Requires-Dist: requests
Requires-Dist: rich
